simpleapi/README.md
simpleapi/__init__.py
simpleapi/core.py
simpleapi/custom_types.py
simpleapi/handler.py
simpleapi/request.py
simpleapi/response.py
simpleapi/router.py
simpleapi/simpleapi.py
simpleapi/utils.py
simplestapi-0.1.5.dist-info/LICENSE
simplestapi-0.1.5.dist-info/METADATA
simplestapi-0.1.5.dist-info/WHEEL
simplestapi-0.1.5.dist-info/RECORD
